djmigrator/__init__.py
djmigrator/apps.py
djmigrator/management/__init__.py
djmigrator/management/commands/__init__.py
djmigrator/management/commands/smart_makemigrations.py
djmigrator/migrations/__init__.py
djmigrator-1.0.7.dist-info/METADATA
djmigrator-1.0.7.dist-info/WHEEL
djmigrator-1.0.7.dist-info/top_level.txt
djmigrator-1.0.7.dist-info/RECORD
