Metadata-Version: 2.4
Name: djmigrator
Version: 1.0.7
Summary: Smart Django migration manager.
Home-page: https://github.com/yourusername/djmigrator
Author: Umakaran
Author-email: umakaranuma1126@gmail.com
Classifier: Framework :: Django
Classifier: Programming Language :: Python :: 3
Classifier: License :: OSI Approved :: MIT License
Requires-Python: >=3.8
Requires-Dist: Django>=4.2
Dynamic: author
Dynamic: author-email
Dynamic: classifier
Dynamic: description
Dynamic: description-content-type
Dynamic: home-page
Dynamic: requires-dist
Dynamic: requires-python
Dynamic: summary
